MANIFEST.in
README.txt
requirements.txt
setup.py
test-requirements.txt
ardana_configurationprocessor/__init__.py
ardana_configurationprocessor.egg-info/PKG-INFO
ardana_configurationprocessor.egg-info/SOURCES.txt
ardana_configurationprocessor.egg-info/dependency_links.txt
ardana_configurationprocessor.egg-info/entry_points.txt
ardana_configurationprocessor.egg-info/not-zip-safe
ardana_configurationprocessor.egg-info/requires.txt
ardana_configurationprocessor.egg-info/top_level.txt
ardana_configurationprocessor/cmd/__init__.py
ardana_configurationprocessor/cmd/ardana_cp.py
ardana_configurationprocessor/cmd/ardana_cp_decrypt.py
ardana_configurationprocessor/cmd/ardana_cp_passwordchecker.py
ardana_configurationprocessor/cp/__init__.py
ardana_configurationprocessor/cp/controller/CloudConfigController.py
ardana_configurationprocessor/cp/controller/CloudNameController.py
ardana_configurationprocessor/cp/controller/NetworkConfigController.py
ardana_configurationprocessor/cp/controller/__init__.py
ardana_configurationprocessor/cp/lib/CloudName.py
ardana_configurationprocessor/cp/lib/DataTransformer.py
ardana_configurationprocessor/cp/lib/__init__.py
ardana_configurationprocessor/cp/model/BuilderPlugin.py
ardana_configurationprocessor/cp/model/CPConfigFile.py
ardana_configurationprocessor/cp/model/CPController.py
ardana_configurationprocessor/cp/model/CPLogging.py
ardana_configurationprocessor/cp/model/CPProcessor.py
ardana_configurationprocessor/cp/model/CPSecurity.py
ardana_configurationprocessor/cp/model/CPSecurityHelper.py
ardana_configurationprocessor/cp/model/CPState.py
ardana_configurationprocessor/cp/model/CPVariables.py
ardana_configurationprocessor/cp/model/CheckpointerPlugin.py
ardana_configurationprocessor/cp/model/Cidr.py
ardana_configurationprocessor/cp/model/CloudDescription.py
ardana_configurationprocessor/cp/model/CloudModel.py
ardana_configurationprocessor/cp/model/ConfigFile.py
ardana_configurationprocessor/cp/model/ConfigFileFormat.py
ardana_configurationprocessor/cp/model/ConfigProcess.py
ardana_configurationprocessor/cp/model/ControlPlane.py
ardana_configurationprocessor/cp/model/DependencyCalculator.py
ardana_configurationprocessor/cp/model/DependencyElement.py
ardana_configurationprocessor/cp/model/DependentNode.py
ardana_configurationprocessor/cp/model/ExplainerPlugin.py
