Metadata-Version: 1.0
Name: ardana-configurationprocessor
Version: 0.4.0
Summary: Configuration Processor for Ardana CLM
Home-page: https://github.com/ArdanaCLM
Author: SUSE LLC
Author-email: ardana@googlegroups.com
License: Apache-2.0
Platform: UNKNOWN
